Metadata-Version: 1.1
Name: wasabi-scenegraph
Version: 0.2.0
Summary: Pure python 3D graphics engine
Home-page: https://bitbucket.org/lordmauve/wasabi-scenegraph
Author: Daniel Pope
Author-email: mauve@mauveweb.co.uk
License: UNKNOWN
Platform: UNKNOWN
Classifier: Development Status :: 3 - Alpha
Classifier: License :: OSI Approved :: GNU Affero General Public License v3 or later (AGPLv3+)
Classifier: Programming Language :: Python :: 2
Classifier: Operating System :: OS Independent
Classifier: Topic :: Software Development :: Libraries :: Python Modules
